Metadata-Version: 1.1
Name: quickviz
Version: 0.3.2
Summary: quickviz: interactive widgets for plotting pandas dataframes.
Home-page: https://github.com/chmduquesne/quickviz
Author: Christophe-Marie Duquesne
Author-email: chmd@chmd.fr
License: MIT
Download-URL: https://github.com/chmduquesne/quickviz
Platform: UNKNOWN
Classifier: Development Status :: 4 - Beta
Classifier: Environment :: Console
Classifier: Intended Audience :: Science/Research
Classifier: License :: OSI Approved :: MIT License
Classifier: Natural Language :: English
Classifier: Programming Language :: Python :: 3.5
